csvlogcleaner-0.1.0.dist-info/METADATA
csvlogcleaner-0.1.0.dist-info/WHEEL
csvlogcleaner/__init__.py
csvlogcleaner/csvlogcleaner.cpython-312-darwin.so
csvlogcleaner-0.1.0.dist-info/RECORD
